angushyxtesttttt-0.1.0.dist-info/METADATA
angushyxtesttttt-0.1.0.dist-info/WHEEL
my_project/__init__.py
angushyxtesttttt-0.1.0.dist-info/RECORD
