Metadata-Version: 2.1
Name: angushyxtesttttt
Version: 0.1.0
Author-Email: angushyx <sickmi14798@gmail.com>
License: MIT
Requires-Python: >=3.8
Requires-Dist: requests>=2.31.0
Requires-Dist: flask>=1.0
Requires-Dist: flask-sqlalchemy>=3.1.1
